DockEva/DockEva.cpp
DockEva/Makefile
DockEva/__init__.py
DockEva/main.py
DockEva/Linux/DockEva
DockEva/Windows/DockEva.exe
DockEva/Windows/DockEva.obj
dockeva-1.2.dist-info/METADATA
dockeva-1.2.dist-info/WHEEL
dockeva-1.2.dist-info/entry_points.txt
dockeva-1.2.dist-info/licenses/LICENSE
dockeva-1.2.dist-info/RECORD
