Metadata-Version: 2.3
Name: DockEva
Version: 1.2
Summary: Calculating the Docking RMSD between two ligands
Project-URL: Homepage, https://github.com/jun-csbio/DockEva
Project-URL: Issues, https://github.com/jun-csbio/DockEva/issues
Author-email: Jun Hu <junh_cs@126.com>
Classifier: License :: OSI Approved :: MIT License
Classifier: Operating System :: OS Independent
Classifier: Programming Language :: Python :: 3
Requires-Python: >=3.7
